taskforge/__init__.py
taskforge/config.py
taskforge/printing.py
taskforge/state.py
taskforge/client/__init__.py
taskforge/client/base.py
taskforge/client/client.py
taskforge/client/context.py
taskforge/client/filter.py
taskforge/client/http.py
taskforge/client/source.py
taskforge/client/tasks.py
taskforge/client/user.py
taskforge/commands/__init__.py
taskforge/commands/add.py
taskforge/commands/cli.py
taskforge/commands/complete.py
taskforge/commands/defer.py
taskforge/commands/edit.py
taskforge/commands/login.py
taskforge/commands/next.py
taskforge/commands/register.py
taskforge/commands/search.py
taskforge/commands/switch_context.py
taskforge/commands/todo.py
taskforge/commands/utils.py
taskforge/commands/work_on.py
taskforge/commands/filters/__init__.py
taskforge/commands/filters/delete.py
taskforge/commands/filters/filters.py
taskforge/commands/filters/list_cmd.py
taskforge/commands/filters/run.py
taskforge/commands/filters/save.py
taskforge/commands/filters/update.py
taskforge_cli-0.3.3.dist-info/METADATA
taskforge_cli-0.3.3.dist-info/WHEEL
taskforge_cli-0.3.3.dist-info/entry_points.txt
taskforge_cli-0.3.3.dist-info/top_level.txt
taskforge_cli-0.3.3.dist-info/zip-safe
taskforge_cli-0.3.3.dist-info/RECORD
