Metadata-Version: 2.1
Name: taskforge-cli
Version: 0.3.3
Summary: A task management tool that automates your workflow
Home-page: https://github.com/taskforge/cli
Author: Mathew Robinson
Author-email: chasinglogic@gmail.com
License: Apache-2.0
Platform: any
Classifier: Development Status :: 4 - Beta
Classifier: Environment :: Console
Classifier: Intended Audience :: Developers
Classifier: License :: OSI Approved :: Apache Software License
Classifier: Operating System :: POSIX
Classifier: Operating System :: MacOS
Classifier: Operating System :: Microsoft :: Windows
Classifier: Programming Language :: Python :: 3
Classifier: Programming Language :: Python :: 3 :: Only
Classifier: Programming Language :: Python :: 3.6
Classifier: Topic :: Software Development :: Libraries :: Python Modules
Requires-Dist: click (==7.1.2)
Requires-Dist: PyYAML (==5.4.1)
Requires-Dist: appdirs (==1.4.4)
Requires-Dist: tabulate (==0.8.9)
Requires-Dist: yaspin (==1.5.0)
Requires-Dist: requests (==2.25.1)
